idasen_ha/__init__.py
idasen_ha/connection_manager.py
idasen_ha/errors.py
idasen_ha/py.typed
idasen_ha-2.6.3.dist-info/LICENSE
idasen_ha-2.6.3.dist-info/METADATA
idasen_ha-2.6.3.dist-info/WHEEL
idasen_ha-2.6.3.dist-info/top_level.txt
idasen_ha-2.6.3.dist-info/RECORD
